<?xml version="1.0" encoding="utf-8"?>
<missing/>
<errors>
 <para id="12">
  <se lang="uk" variant_id="0">
   Fond Lit., which lay wide open to a snapshot of a Russian. pasture with Lyov Tolstoy trudging across it toward the camera and some long-maned horses behind him, their innocent heads turned toward the photographer too.
  </se>
  <se lang="ru" variant_id="1">
   Fond Lit., раскрывшийся на фотографии русского луга, по которому прямо на фотокамеру брел Лев Толстой, а за его спиной — какието долгогривые лошади, тоже обратившие к фотографу свои невинные морды.
  </se>
 </para>
 <para id="13">
  <se lang="uk" variant_id="0">
   V boyu li, v stranstvii, v volnah?
  </se>
  <se lang="ru" variant_id="1">
   V boyu li, v stranstvii, v volnah?
  </se>
 </para>
 <para id="27">
  <se lang="uk" variant_id="0">
   'I have not heard. Mrs Fire, permit me to ask вЂ” '
  </se>
  <se lang="ru" variant_id="1">
   — Я не услышал, миссис Файэр, разрешите мне спрашивать...
  </se>
 </para>
 <para id="39">
  <se lang="uk" variant_id="0">
   '18, 19,' muttered Pnin.
  </se>
  <se lang="ru" variant_id="1">
   — Восемнадцатый, девятнадцатый, — бормотал Пнин.
  </se>
 </para>
 <para id="40">
  <se lang="uk" variant_id="0">
   'There is not great difference!
  </se>
  <se lang="ru" variant_id="1">
   — Не есть много разницы!
  </se>
 </para>
 <para id="70">
  <se lang="uk" variant_id="0">
   Pnin pocketed his index card and, while doing so, recalled without any prompting what he had not been able to recall a while ago:
  </se>
  <se lang="ru" variant_id="1">
   Пнин засунул карточку в карман и, совершая эту операцию, вспомнил вдруг без всякой подсказки то, чего только что никак не мог припомнить:
  </se>
 </para>
 <para id="71">
  <se lang="uk" variant_id="0">
   ...plГЇla i pela, pela i plГЇla...
  </se>
  <se lang="ru" variant_id="1">
   "...plila i pela, pela i plila
  </se>
 </para>
</errors>