<?xml version="1.0" encoding="utf-8"?>
<missing/>
<errors>
 <para id="40">
  <se lang="uk" variant_id="0">
   Stored in its strongholds through the years. Instead
  </se>
  <se lang="ru" variant_id="1">
   Взять в слуги рассудительность свою
  </se>
 </para>
 <para id="83">
  <se lang="uk" variant_id="0">
   Grieves on the brink of a remembered pond
  </se>
  <se lang="ru" variant_id="1">
   Теперь навек ребенка.
  </se>
 </para>
 <para id="84">
  <se lang="uk" variant_id="0">
   Full of a dreamy sky.
  </se>
  <se lang="ru" variant_id="1">
   Вновь — вопрос:
  </se>
 </para>
 <para id="85">
  <se lang="uk" variant_id="0">
   And, also blond,
  </se>
  <se lang="ru" variant_id="1">
   Что Время? — рост?
  </se>
 </para>
 <para id="86">
  <se lang="uk" variant_id="0">
   But with a touch of tawny in the shade,
  </se>
  <se lang="ru" variant_id="1">
   Но что для рая — рост?
  </se>
 </para>
 <para id="92">
  <se lang="uk" variant_id="0">
   What toy To give the babe?
  </se>
  <se lang="ru" variant_id="1">
   Какую погремушку иль слова Для малыша найти?
  </se>
 </para>
 <para id="149">
  <se lang="uk" variant_id="0">
   And an old Communist. Iph could at least
  </se>
  <se lang="ru" variant_id="1">
   Его ль устав иль партии устав —
  </se>
 </para>
 <para id="152">
  <se lang="uk" variant_id="0">
   Buddhism took root. A medium smuggled in
  </se>
  <se lang="ru" variant_id="1">
   Взял верх буддизм — коктейль из двух чудес:
  </se>
 </para>
 <para id="160">
  <se lang="uk" variant_id="0">
   Of deathвЂ™s abyss.
  </se>
  <se lang="ru" variant_id="1">
   Отбросить.
  </se>
 </para>
 <para id="172">
  <se lang="uk" variant_id="0">
   "IвЂ™m sure itвЂ™s not the shutter.
  </se>
  <se lang="ru" variant_id="1">
   — Давай. — Да разве ветер?
  </se>
 </para>
 <para id="173">
  <se lang="uk" variant_id="0">
   There вЂ” again."
  </se>
  <se lang="ru" variant_id="1">
   Нет, наверняка!
  </se>
 </para>
 <para id="198">
  <se lang="uk" variant_id="0">
   Of college education. You went on
  </se>
  <se lang="ru" variant_id="1">
   Ты делала французский перевод
  </se>
 </para>
 <para id="202">
  <se lang="uk" variant_id="0">
   Mars glowed. Shahs married.
  </se>
  <se lang="ru" variant_id="1">
   Шпионил сонм угрюмых россиян;
  </se>
 </para>
 <para id="216">
  <se lang="uk" variant_id="0">
   There sat by chance
  </se>
  <se lang="ru" variant_id="1">
   Как раз
  </se>
 </para>
 <para id="217">
  <se lang="uk" variant_id="0">
   A doctor in the front row.
  </se>
  <se lang="ru" variant_id="1">
   У сцены доктор был —
  </se>
 </para>
 <para id="224">
  <se lang="uk" variant_id="0">
   Give me now
  </se>
  <se lang="ru" variant_id="1">
   Теперь —
  </se>
 </para>
 <para id="225">
  <se lang="uk" variant_id="0">
   Your full attention.
  </se>
  <se lang="ru" variant_id="1">
   вниманье!
  </se>
 </para>
 <para id="226">
  <se lang="uk" variant_id="0">
   I canвЂ™t tell you how
  </se>
  <se lang="ru" variant_id="1">
   Я не знаю, как
  </se>
 </para>
 <para id="227">
  <se lang="uk" variant_id="0">
   I knew вЂ” but I did know that I had crossed
  </se>
  <se lang="ru" variant_id="1">
   Я знал, но знаю: я ступил за знак
  </se>
 </para>
 <para id="235">
  <se lang="uk" variant_id="0">
   Within one stem. And dreadfully distinct
  </se>
  <se lang="ru" variant_id="1">
   И, страшно различимый в темноте,
  </se>
 </para>
 <para id="260">
  <se lang="uk" variant_id="0">
  </se>
  <se lang="ru" variant_id="1">
  </se>
 </para>
 <para id="262">
  <se lang="uk" variant_id="0">
   He smiled.
  </se>
  <se lang="ru" variant_id="1">
  </se>
 </para>
 <para id="263">
  <se lang="uk" variant_id="0">
   "Not quite: just half a shade," he said.
  </se>
  <se lang="ru" variant_id="1">
   «Полуушедшим, мистер Шейд, туда».
  </se>
 </para>
 <para id="264">
  <se lang="uk" variant_id="0">
   However, I demurred. In mind I kept
  </se>
  <se lang="ru" variant_id="1">
   Однако я отсрочил приговор,
  </se>
 </para>
 <para id="283">
  <se lang="uk" variant_id="0">
   Old Faithful!
  </se>
  <se lang="ru" variant_id="1">
   И я был рад.
  </se>
 </para>
 <para id="284">
  <se lang="uk" variant_id="0">
   And its presence always would
  </se>
  <se lang="ru" variant_id="1">
  </se>
 </para>
 <para id="285">
  <se lang="uk" variant_id="0">
   Console me wonderfully. Then, one day,
  </se>
  <se lang="ru" variant_id="1">
   И мне был дан потом
  </se>
 </para>
 <para id="286">
  <se lang="uk" variant_id="0">
   I came across what seemed a twin display.
  </se>
  <se lang="ru" variant_id="1">
   Вторичной демонстрации фантом.
  </se>
 </para>
 <para id="288">
  <se lang="uk" variant_id="0">
   About a Mrs. Z.
  </se>
  <se lang="ru" variant_id="1">
   о миссис Z —
  </se>
 </para>
 <para id="289">
  <se lang="uk" variant_id="0">
   whose heart had been
  </se>
  <se lang="ru" variant_id="1">
   причем,
  </se>
 </para>
 <para id="309">
  <se lang="uk" variant_id="0">
   To Jim
  </se>
  <se lang="ru" variant_id="1">
  </se>
 </para>
 <para id="320">
  <se lang="uk" variant_id="0">
   Of me to come! I desperately tried
  </se>
  <se lang="ru" variant_id="1">
   Задать
  </se>
 </para>
 <para id="340">
  <se lang="uk" variant_id="0">
   I might Have made her tell me more about the white
  </se>
  <se lang="ru" variant_id="1">
   Чтоб получить ответ на свой вопрос
  </se>
 </para>
 <para id="384">
  <se lang="uk" variant_id="0">
   Glasses or pipe. Coordinating these
  </se>
  <se lang="ru" variant_id="1">
   И этот факт, и этот вот предмет
  </se>
 </para>
 <para id="386">
  <se lang="uk" variant_id="0">
   And vanished objects. Making ornaments
  </se>
  <se lang="ru" variant_id="1">
   Случайное в орнамент сплетено
  </se>
 </para>
</errors>